mistapi/__api_request.py
mistapi/__api_response.py
mistapi/__api_session.py
mistapi/__init__.py
mistapi/__logger.py
mistapi/__pagination.py
mistapi/__version.py
mistapi/cli.py
mistapi/__models/__init__.py
mistapi/__models/privilege.py
mistapi/api/__init__.py
mistapi/api/v1/__init__.py
mistapi/api/v1/const/__init__.py
mistapi/api/v1/const/alarm_defs.py
mistapi/api/v1/const/ap_channels.py
mistapi/api/v1/const/ap_esl_versions.py
mistapi/api/v1/const/ap_led_status.py
mistapi/api/v1/const/app_categories.py
mistapi/api/v1/const/app_subcategories.py
mistapi/api/v1/const/applications.py
mistapi/api/v1/const/client_events.py
mistapi/api/v1/const/countries.py
mistapi/api/v1/const/default_gateway_config.py
mistapi/api/v1/const/device_events.py
mistapi/api/v1/const/device_models.py
mistapi/api/v1/const/fingerprint_types.py
mistapi/api/v1/const/gateway_applications.py
mistapi/api/v1/const/insight_metrics.py
mistapi/api/v1/const/languages.py
mistapi/api/v1/const/license_types.py
mistapi/api/v1/const/marvisclient_versions.py
mistapi/api/v1/const/mxedge_events.py
mistapi/api/v1/const/mxedge_models.py
mistapi/api/v1/const/nac_events.py
mistapi/api/v1/const/otherdevice_events.py
mistapi/api/v1/const/otherdevice_models.py
mistapi/api/v1/const/states.py
mistapi/api/v1/const/system_events.py
mistapi/api/v1/const/traffic_types.py
mistapi/api/v1/const/webhook_topics.py
mistapi/api/v1/installer/__init__.py
mistapi/api/v1/installer/orgs/__init__.py
mistapi/api/v1/installer/orgs/alarmtemplates.py
mistapi/api/v1/installer/orgs/deviceprofiles.py
mistapi/api/v1/installer/orgs/devices.py
mistapi/api/v1/installer/orgs/rftemplates.py
mistapi/api/v1/installer/orgs/sitegroups.py
mistapi/api/v1/installer/orgs/sites.py
mistapi/api/v1/installer/sites/__init__.py
mistapi/api/v1/installer/sites/optimize.py
mistapi/api/v1/invite/__init__.py
mistapi/api/v1/invite/verify.py
mistapi/api/v1/login/__init__.py
mistapi/api/v1/login/login.py
mistapi/api/v1/login/lookup.py
mistapi/api/v1/login/oauth.py
mistapi-0.59.5.dist-info/METADATA
mistapi-0.59.5.dist-info/WHEEL
mistapi-0.59.5.dist-info/licenses/LICENSE
mistapi-0.59.5.dist-info/RECORD
