Metadata-Version: 2.4
Name: mistapi
Version: 0.59.5
Summary: Python package to simplify the Mist System APIs usage
Project-URL: Source, https://github.com/tmunzer/mistapi_python
Project-URL: Bug Tracker, https://github.com/tmunzer/mistapi_python/issues
Author-email: Thomas Munzer <tmunzer@juniper.net>
License: MIT License
License-File: LICENSE
Keywords: API,Juniper,Mist
Classifier: Development Status :: 4 - Beta
Classifier: Intended Audience :: System Administrators
Classifier: Intended Audience :: Telecommunications Industry
Classifier: License :: OSI Approved :: MIT License
Classifier: Operating System :: OS Independent
Classifier: Programming Language :: Python :: 3
Classifier: Topic :: System :: Networking
Requires-Python: >=3.10
Requires-Dist: deprecation>=2.1.0
Requires-Dist: hvac>=2.3.0
Requires-Dist: keyring>=24.3.0
Requires-Dist: python-dotenv>=1.1.0
Requires-Dist: requests>=2.32.3
Requires-Dist: tabulate>=0.9.0
